GoogleNews/__init__.py
test/__init__.py
test/test_search.py
test/test_sort.py
GoogleNews-1.6.13.dist-info/LICENSE
GoogleNews-1.6.13.dist-info/METADATA
GoogleNews-1.6.13.dist-info/WHEEL
GoogleNews-1.6.13.dist-info/top_level.txt
GoogleNews-1.6.13.dist-info/RECORD
