Metadata-Version: 2.1
Name: GoogleNews
Version: 1.6.13
Summary: Google News search for Python
Home-page: https://github.com/Iceloof/GoogleNews
Author: Hurin Hu
Author-email: hurin@live.ca
Classifier: Programming Language :: Python :: 3.6
Classifier: License :: OSI Approved :: MIT License
Classifier: Operating System :: OS Independent
License-File: LICENSE
Requires-Dist: beautifulsoup4
Requires-Dist: dateparser
Requires-Dist: python-dateutil
